{
	"info": {
		"_postman_id": "94040210-5d58-4563-9039-83b950565354",
		"name": "Udacity C4 Project",
		"schema": "https://schema.getpostman.com/json/collection/v2.1.0/collection.json"
	},
	"item": [
		{
			"name": "TODOs",
			"item": [
				{
					"name": "Get all todos",
					"request": {
						"method": "GET",
						"header": [
							{
								"key": "Authorization",
								"value": "Bearer {{authToken}}",
								"type": "text"
							}
						],
						"url": {
							"raw": "https://{{apiId}}.execute-api.eu-central-1.amazonaws.com/dev/todos",
							"protocol": "https",
							"host": [
								"{{apiId}}",
								"execute-api",
								"eu-central-1",
								"amazonaws",
								"com"
							],
							"path": [
								"dev",
								"todos"
							]
						}
					},
					"response": []
				},
				{
					"name": "Create todo",
					"request": {
						"method": "POST",
						"header": [
							{
								"key": "Content-Type",
								"name": "Content-Type",
								"value": "application/json",
								"type": "text"
							},
							{
								"key": "Authorization",
								"value": "Bearer {{authToken}}",
								"type": "text"
							}
						],
						"body": {
							"mode": "raw",
							"raw": "{\n\t\"name\": \"Water flowers\",\n\t\"dueDate\": \"2019-06-11\"\n}"
						},
						"url": {
							"raw": "https://{{apiId}}.execute-api.eu-central-1.amazonaws.com/dev/todos",
							"protocol": "https",
							"host": [
								"{{apiId}}",
								"execute-api",
								"eu-central-1",
								"amazonaws",
								"com"
							],
							"path": [
								"dev",
								"todos"
							]
						}
					},
					"response": []
				},
				{
					"name": "Update todo",
					"request": {
						"method": "PATCH",
						"header": [
							{
								"key": "Content-Type",
								"name": "Content-Type",
								"type": "text",
								"value": "application/json"
							},
							{
								"key": "Authorization",
								"type": "text",
								"value": "Bearer {{authToken}}"
							}
						],
						"body": {
							"mode": "raw",
							"raw": "{\n\t\"name\": \"Change the world - that's the other one\",\n\t\"dueDate\": \"2019-12-11\",\n\t\"done\": true\n}"
						},
						"url": {
							"raw": "https://{{apiId}}.execute-api.eu-central-1.amazonaws.com/dev/todos/aac0b060-409c-471a-9cbb-97e158632f3c",
							"protocol": "https",
							"host": [
								"{{apiId}}",
								"execute-api",
								"eu-central-1",
								"amazonaws",
								"com"
							],
							"path": [
								"dev",
								"todos",
								"aac0b060-409c-471a-9cbb-97e158632f3c"
							]
						}
					},
					"response": []
				},
				{
					"name": "Delete todo",
					"request": {
						"method": "DELETE",
						"header": [
							{
								"key": "Content-Type",
								"name": "Content-Type",
								"type": "text",
								"value": "application/json"
							},
							{
								"key": "Authorization",
								"type": "text",
								"value": "Bearer {{authToken}}"
							}
						],
						"body": {
							"mode": "raw",
							"raw": ""
						},
						"url": {
							"raw": "https://{{apiId}}.execute-api.eu-central-1.amazonaws.com/dev/todos/a7586ebf-429b-4705-802d-041e92f29250",
							"protocol": "https",
							"host": [
								"{{apiId}}",
								"execute-api",
								"eu-central-1",
								"amazonaws",
								"com"
							],
							"path": [
								"dev",
								"todos",
								"a7586ebf-429b-4705-802d-041e92f29250"
							]
						}
					},
					"response": []
				},
				{
					"name": "Get attachment URL",
					"request": {
						"method": "POST",
						"header": [
							{
								"key": "Authorization",
								"value": "Bearer {{authToken}}",
								"type": "text"
							}
						],
						"body": {
							"mode": "raw",
							"raw": ""
						},
						"url": {
							"raw": "https://{{apiId}}.execute-api.us-east-1.amazonaws.com/dev/todos/3836b777-9bc4-4429-9b79-ba4e4f5f91c0/attachment",
							"protocol": "https",
							"host": [
								"{{apiId}}",
								"execute-api",
								"us-east-1",
								"amazonaws",
								"com"
							],
							"path": [
								"dev",
								"todos",
								"3836b777-9bc4-4429-9b79-ba4e4f5f91c0",
								"attachment"
							]
						}
					},
					"response": []
				}
			],
			"event": [
				{
					"listen": "prerequest",
					"script": {
						"type": "text/javascript",
						"exec": [
							""
						]
					}
				},
				{
					"listen": "test",
					"script": {
						"type": "text/javascript",
						"exec": [
							""
						]
					}
				}
			]
		}
	],
	"event": [
		{
			"listen": "prerequest",
			"script": {
				"type": "text/javascript",
				"exec": [
					""
				]
			}
		},
		{
			"listen": "test",
			"script": {
				"type": "text/javascript",
				"exec": [
					""
				]
			}
		}
	],
	"variable": [
		{
			"key": "apiId",
			"value": "3uere66bf6"
		},
		{
			"key": "authToken",
			"value": ""
		}
	]
}